{
  "credits": [{
      "author": {
        "name": "FoxSynergy",
        "email": "",
        "type": "track sound",
        "url": [
          "https://opengameart.org/content/never-stop-running-8-bit",
          "https://opengameart.org/content/retro-samurai-8-bit"
        ]
      }
    },
    {
      "author": {
        "name": "cynicmusic",
        "email": "",
        "type": "track sound",
        "url": [
          "https://opengameart.org/content/enchanted-tiki-86",
          "cynicmusic.com"
        ]
      }
    },
    {
      "author": {
        "name": "Mopz",
        "email": "",
        "type": "track sound",
        "url": ["https://opengameart.org/content/kuno-game-music"]
      }
    },
    {
      "author": {
        "name": "bart",
        "email": "",
        "type": "track sound",
        "url": [
          "https://opengameart.org/content/the-adventure-begins-8-bit-remix"
        ]
      }
    },
    {
      "author": {
        "name": "Daniel Stephens",
        "email": "",
        "type": "track sound",
        "url": ["https://opengameart.org/content/summer-park-8bit-tune-loop"]
      }
    },
    {
      "author": {
        "name": "t4ngr4m",
        "email": "",
        "type": "track sound",
        "url": ["https://opengameart.org/content/generic-8-bit-jrpg-soundtrack"]
      }
    },
    {
      "author": {
        "name": "Joseph Pueyo",
        "email": "allyourbeats01@gmail.com",
        "type": "track sound",
        "url": [
          "https://opengameart.org/content/this-game-is-over",
          "http://www.josephpueyo.com"
        ]
      }
    },
    {
      "author": {
        "name": "qubodup",
        "email": "",
        "type": "track sound",
        "url": ["https://opengameart.org/content/click-ui-menu-sfx-yesnoselect"]
      }
    },
    {
      "author": {
        "name": "NenadSimic",
        "email": "",
        "type": "track sound",
        "url": ["https://opengameart.org/content/menu-selection-click"]
      }
    },
    {
      "author": {
        "name": "Jesús Lastra",
        "email": "",
        "type": "track sound",
        "url": ["https://opengameart.org/content/sound-effects-sfx025"]
      }
    },
    {
      "author": {
        "name": "Bobjt",
        "email": "",
        "type": "track sound",
        "url": [
          "https://opengameart.org/content/frozen-orchard",
          "http://bobjt.com"
        ]
      }
    },
    {
      "author": {
        "name": "MrAlex99",
        "email": "",
        "type": "track sound",
        "url": [
          "https://opengameart.org/content/dark-scene"
        ]
      }
    },
    {
      "author": {
        "name": "Enprogames",
        "email": "",
        "type": "track sound",
        "url": [
          "https://opengameart.org/content/jungle-music"
        ]
      }
    },
    {
      "author": {
        "name": "Nia Mi",
        "email": "",
        "type": "track sound",
        "url": [
          "https://opengameart.org/content/fun-background"
        ]
      }
    },
    {
      "author": {
        "name": "TinyWorlds",
        "email": "",
        "type": "track sound",
        "url": [
          "https://opengameart.org/content/happy-adventure-loop"
        ]
      }
    },
    {
      "author": {
        "name": "OwlishMedia",
        "email": "",
        "type": "track sound",
        "url": [
          "https://opengameart.org/content/202-more-sound-effects"
        ]
      }
    }, {
      "author": {
        "name": "sujit1717",
        "email": "",
        "type": "art pack",
        "url": [
          "https://opengameart.org/content/ultimate-platformer-game-artassets-pack-by-unlucky-studio"
        ]
      }
    }
  ]
}
